dmit/__init__.py
dmit/datetools.py
dmit/geotools.py
dmit/ostools.py
dmit/regrot.py
dmit/calc/__init__.py
dmit/calc/pressure.py
dmit/calc/sun.py
dmit/calc/vanulden.py
dmit/dmitio/__init__.py
dmit/stats/__init__.py
dmit/stats/fss.py
dmit-0.5.1.dist-info/LICENSE
dmit-0.5.1.dist-info/METADATA
dmit-0.5.1.dist-info/WHEEL
dmit-0.5.1.dist-info/top_level.txt
dmit-0.5.1.dist-info/RECORD
