Metadata-Version: 2.1
Name: dmit
Version: 0.5.1
Summary: A Met Tool package
Home-page: UNKNOWN
Author: Kasper Hintz
Author-email: kah@dmi.dk
License: UNKNOWN
Platform: UNKNOWN
Classifier: Programming Language :: Python :: 3
Classifier: License :: OSI Approved :: MIT License
Classifier: Operating System :: OS Independent
License-File: LICENSE
Requires-Dist: wheel
Requires-Dist: scipy
Requires-Dist: numpy
Requires-Dist: boto3
